[1,["55ae990e-a3b8-484d-8f5d-dd646455c392@6c48a"],["_textureSource"],["cc.SpriteFrame","cc.SpriteAtlas"],0,[[[{"name":"LoadingPage","spriteFrames":["LoadingPage1","b1543c68-0bc1-41de-867a-d46f4b32ddc4@22e40","LoadingPage2","b1543c68-0bc1-41de-867a-d46f4b32ddc4@77ddb","LoadingPage3","b1543c68-0bc1-41de-867a-d46f4b32ddc4@9ea87","LoadingPage4","b1543c68-0bc1-41de-867a-d46f4b32ddc4@76acf","ZeusLoadingUIBG","b1543c68-0bc1-41de-867a-d46f4b32ddc4@e2cde"]}],[1],0,[],[],[]],[[{"name":"LoadingPage1","rect":{"x":425,"y":1,"width":444,"height":55},"offset":{"x":0,"y":0},"originalSize":{"width":444,"height":55},"rotated":false,"capInsets":[0,0,0,0],"vertices":{"rawPosition":[],"indexes":[],"uv":[],"nuv":[],"minPos":{"x":0,"y":0,"z":0},"maxPos":{"x":0,"y":0,"z":0}},"packable":true,"pixelsToUnit":100,"pivot":{"x":0.5,"y":0.5},"meshType":0}],[0],0,[0],[0],[0]],[[{"name":"LoadingPage4","rect":{"x":1,"y":641,"width":589,"height":1016},"offset":{"x":0,"y":0},"originalSize":{"width":589,"height":1016},"rotated":true,"capInsets":[0,0,0,0],"vertices":{"rawPosition":[],"indexes":[],"uv":[],"nuv":[],"minPos":{"x":0,"y":0,"z":0},"maxPos":{"x":0,"y":0,"z":0}},"packable":true,"pixelsToUnit":100,"pivot":{"x":0.5,"y":0.5},"meshType":0}],[0],0,[0],[0],[0]],[[{"name":"LoadingPage2","rect":{"x":1,"y":1,"width":422,"height":32},"offset":{"x":0,"y":0},"originalSize":{"width":422,"height":32},"rotated":false,"capInsets":[0,0,0,0],"vertices":{"rawPosition":[],"indexes":[],"uv":[],"nuv":[],"minPos":{"x":0,"y":0,"z":0},"maxPos":{"x":0,"y":0,"z":0}},"packable":true,"pixelsToUnit":100,"pivot":{"x":0.5,"y":0.5},"meshType":0}],[0],0,[0],[0],[0]],[[{"name":"LoadingPage3","rect":{"x":871,"y":1,"width":102,"height":96},"offset":{"x":0,"y":0},"originalSize":{"width":102,"height":96},"rotated":false,"capInsets":[0,0,0,0],"vertices":{"rawPosition":[],"indexes":[],"uv":[],"nuv":[],"minPos":{"x":0,"y":0,"z":0},"maxPos":{"x":0,"y":0,"z":0}},"packable":true,"pixelsToUnit":100,"pivot":{"x":0.5,"y":0.5},"meshType":0}],[0],0,[0],[0],[0]],[[{"name":"ZeusLoadingUIBG","rect":{"x":1,"y":99,"width":540,"height":960},"offset":{"x":0,"y":0},"originalSize":{"width":540,"height":960},"rotated":true,"capInsets":[0,0,0,0],"vertices":{"rawPosition":[],"indexes":[],"uv":[],"nuv":[],"minPos":{"x":0,"y":0,"z":0},"maxPos":{"x":0,"y":0,"z":0}},"packable":true,"pixelsToUnit":100,"pivot":{"x":0.5,"y":0.5},"meshType":0}],[0],0,[0],[0],[0]]]]
